Metadata-Version: 2.4
Name: half_orm_dev
Version: 0.17.3a9
Summary: half_orm development Framework.
Author-email: Joël Maïzi <joel.maizi@collorg.org>
License-Expression: GPL-3.0-or-later
Project-URL: Homepage, https://github.com/collorg/halfORM_dev
Keywords: postgres,relation-object mapping
Classifier: Development Status :: 3 - Alpha
Classifier: Intended Audience :: Developers
Classifier: Topic :: Software Development :: Build Tools
Classifier: Programming Language :: Python :: 3.9
Classifier: Programming Language :: Python :: 3.10
Classifier: Programming Language :: Python :: 3.11
Classifier: Programming Language :: Python :: 3.12
Classifier: Programming Language :: Python :: 3.13
Classifier: Programming Language :: Python :: 3.14
Requires-Python: >=3.9
License-File: LICENSE
License-File: AUTHORS
Requires-Dist: GitPython
Requires-Dist: click
Requires-Dist: pydash
Requires-Dist: pytest
Requires-Dist: half_orm<0.18.0,>=0.17.3
Requires-Dist: tomli>=2.0.0; python_version < "3.11"
Requires-Dist: tomli_w>=1.0.0
Dynamic: license-file
Dynamic: requires-dist
